package serp.bytecode;

public interface Constants {
   int VALID_MAGIC = -889275714;
   int MAJOR_VERSION = 45;
   int MINOR_VERSION = 3;
   int MAJOR_VERSION_JAVA5 = 49;
   int MINOR_VERSION_JAVA5 = 0;
   int ACCESS_PUBLIC = 1;
   int ACCESS_PRIVATE = 2;
   int ACCESS_PROTECTED = 4;
   int ACCESS_STATIC = 8;
   int ACCESS_FINAL = 16;
   int ACCESS_SUPER = 32;
   int ACCESS_SYNCHRONIZED = 32;
   int ACCESS_VOLATILE = 64;
   int ACCESS_BRIDGE = 64;
   int ACCESS_TRANSIENT = 128;
   int ACCESS_VARARGS = 128;
   int ACCESS_NATIVE = 256;
   int ACCESS_INTERFACE = 512;
   int ACCESS_ABSTRACT = 1024;
   int ACCESS_STRICT = 2048;
   int ACCESS_SYNTHETIC = 4096;
   int ACCESS_ANNOTATION = 8192;
   int ACCESS_ENUM = 16384;
   String ATTR_CODE = "Code";
   String ATTR_CONST = "ConstantValue";
   String ATTR_DEPRECATED = "Deprecated";
   String ATTR_EXCEPTIONS = "Exceptions";
   String ATTR_INNERCLASS = "InnerClasses";
   String ATTR_LINENUMBERS = "LineNumberTable";
   String ATTR_LOCALS = "LocalVariableTable";
   String ATTR_LOCAL_TYPES = "LocalVariableTypeTable";
   String ATTR_SOURCE = "SourceFile";
   String ATTR_SYNTHETIC = "Synthetic";
   String ATTR_UNKNOWN = "Unknown";
   String ATTR_ANNOTATIONS = "RuntimeInvisibleAnnotations";
   String ATTR_RUNTIME_ANNOTATIONS = "RuntimeVisibleAnnotations";
   String ATTR_BOOTSTRAP_METHODS = "BootstrapMethods";
   int METHODHANDLE_REF_GETFIELD = 1;
   int METHODHANDLE_REF_GETSTATIC = 2;
   int METHODHANDLE_REF_PUTFIELD = 3;
   int METHODHANDLE_REF_PUTSTATIC = 4;
   int METHODHANDLE_REF_INVOKEVIRTUAL = 5;
   int METHODHANDLE_REF_INVOKESTATIC = 6;
   int METHODHANDLE_REF_INVOKESPECIAL = 7;
   int METHODHANDLE_REF_NEWINVOKESPECIAL = 8;
   int METHODHANDLE_REF_INVOKEINTERFACE = 9;
   int NOP = 0;
   int ACONSTNULL = 1;
   int ICONSTM1 = 2;
   int ICONST0 = 3;
   int ICONST1 = 4;
   int ICONST2 = 5;
   int ICONST3 = 6;
   int ICONST4 = 7;
   int ICONST5 = 8;
   int LCONST0 = 9;
   int LCONST1 = 10;
   int FCONST0 = 11;
   int FCONST1 = 12;
   int FCONST2 = 13;
   int DCONST0 = 14;
   int DCONST1 = 15;
   int BIPUSH = 16;
   int SIPUSH = 17;
   int LDC = 18;
   int LDCW = 19;
   int LDC2W = 20;
   int ILOAD = 21;
   int LLOAD = 22;
   int FLOAD = 23;
   int DLOAD = 24;
   int ALOAD = 25;
   int ILOAD0 = 26;
   int ILOAD1 = 27;
   int ILOAD2 = 28;
   int ILOAD3 = 29;
   int LLOAD0 = 30;
   int LLOAD1 = 31;
   int LLOAD2 = 32;
   int LLOAD3 = 33;
   int FLOAD0 = 34;
   int FLOAD1 = 35;
   int FLOAD2 = 36;
   int FLOAD3 = 37;
   int DLOAD0 = 38;
   int DLOAD1 = 39;
   int DLOAD2 = 40;
   int DLOAD3 = 41;
   int ALOAD0 = 42;
   int ALOAD1 = 43;
   int ALOAD2 = 44;
   int ALOAD3 = 45;
   int IALOAD = 46;
   int LALOAD = 47;
   int FALOAD = 48;
   int DALOAD = 49;
   int AALOAD = 50;
   int BALOAD = 51;
   int CALOAD = 52;
   int SALOAD = 53;
   int ISTORE = 54;
   int LSTORE = 55;
   int FSTORE = 56;
   int DSTORE = 57;
   int ASTORE = 58;
   int ISTORE0 = 59;
   int ISTORE1 = 60;
   int ISTORE2 = 61;
   int ISTORE3 = 62;
   int LSTORE0 = 63;
   int LSTORE1 = 64;
   int LSTORE2 = 65;
   int LSTORE3 = 66;
   int FSTORE0 = 67;
   int FSTORE1 = 68;
   int FSTORE2 = 69;
   int FSTORE3 = 70;
   int DSTORE0 = 71;
   int DSTORE1 = 72;
   int DSTORE2 = 73;
   int DSTORE3 = 74;
   int ASTORE0 = 75;
   int ASTORE1 = 76;
   int ASTORE2 = 77;
   int ASTORE3 = 78;
   int IASTORE = 79;
   int LASTORE = 80;
   int FASTORE = 81;
   int DASTORE = 82;
   int AASTORE = 83;
   int BASTORE = 84;
   int CASTORE = 85;
   int SASTORE = 86;
   int POP = 87;
   int POP2 = 88;
   int DUP = 89;
   int DUPX1 = 90;
   int DUPX2 = 91;
   int DUP2 = 92;
   int DUP2X1 = 93;
   int DUP2X2 = 94;
   int SWAP = 95;
   int IADD = 96;
   int LADD = 97;
   int FADD = 98;
   int DADD = 99;
   int ISUB = 100;
   int LSUB = 101;
   int FSUB = 102;
   int DSUB = 103;
   int IMUL = 104;
   int LMUL = 105;
   int FMUL = 106;
   int DMUL = 107;
   int IDIV = 108;
   int LDIV = 109;
   int FDIV = 110;
   int DDIV = 111;
   int IREM = 112;
   int LREM = 113;
   int FREM = 114;
   int DREM = 115;
   int INEG = 116;
   int LNEG = 117;
   int FNEG = 118;
   int DNEG = 119;
   int ISHL = 120;
   int LSHL = 121;
   int ISHR = 122;
   int LSHR = 123;
   int IUSHR = 124;
   int LUSHR = 125;
   int IAND = 126;
   int LAND = 127;
   int IOR = 128;
   int LOR = 129;
   int IXOR = 130;
   int LXOR = 131;
   int IINC = 132;
   int I2L = 133;
   int I2F = 134;
   int I2D = 135;
   int L2I = 136;
   int L2F = 137;
   int L2D = 138;
   int F2I = 139;
   int F2L = 140;
   int F2D = 141;
   int D2I = 142;
   int D2L = 143;
   int D2F = 144;
   int I2B = 145;
   int I2C = 146;
   int I2S = 147;
   int LCMP = 148;
   int FCMPL = 149;
   int FCMPG = 150;
   int DCMPL = 151;
   int DCMPG = 152;
   int IFEQ = 153;
   int IFNE = 154;
   int IFLT = 155;
   int IFGE = 156;
   int IFGT = 157;
   int IFLE = 158;
   int IFICMPEQ = 159;
   int IFICMPNE = 160;
   int IFICMPLT = 161;
   int IFICMPGE = 162;
   int IFICMPGT = 163;
   int IFICMPLE = 164;
   int IFACMPEQ = 165;
   int IFACMPNE = 166;
   int GOTO = 167;
   int JSR = 168;
   int RET = 169;
   int TABLESWITCH = 170;
   int LOOKUPSWITCH = 171;
   int IRETURN = 172;
   int LRETURN = 173;
   int FRETURN = 174;
   int DRETURN = 175;
   int ARETURN = 176;
   int RETURN = 177;
   int GETSTATIC = 178;
   int PUTSTATIC = 179;
   int GETFIELD = 180;
   int PUTFIELD = 181;
   int INVOKEVIRTUAL = 182;
   int INVOKESPECIAL = 183;
   int INVOKESTATIC = 184;
   int INVOKEINTERFACE = 185;
   int INVOKEDYNAMIC = 186;
   int NEW = 187;
   int NEWARRAY = 188;
   int ANEWARRAY = 189;
   int ARRAYLENGTH = 190;
   int ATHROW = 191;
   int CHECKCAST = 192;
   int INSTANCEOF = 193;
   int MONITORENTER = 194;
   int MONITOREXIT = 195;
   int WIDE = 196;
   int MULTIANEWARRAY = 197;
   int IFNULL = 198;
   int IFNONNULL = 199;
   int GOTOW = 200;
   int JSRW = 201;
   int ARRAY_BOOLEAN = 4;
   int ARRAY_CHAR = 5;
   int ARRAY_FLOAT = 6;
   int ARRAY_DOUBLE = 7;
   int ARRAY_BYTE = 8;
   int ARRAY_SHORT = 9;
   int ARRAY_INT = 10;
   int ARRAY_LONG = 11;
   int MATH_ADD = 96;
   int MATH_SUB = 100;
   int MATH_MUL = 104;
   int MATH_DIV = 108;
   int MATH_REM = 112;
   int MATH_NEG = 116;
   int MATH_SHL = 120;
   int MATH_SHR = 122;
   int MATH_USHR = 124;
   int MATH_AND = 126;
   int MATH_OR = 128;
   int MATH_XOR = 130;
   String[] OPCODE_NAMES = new String[]{"nop", "aconstnull", "iconstm1", "iconst0", "iconst1", "iconst2", "iconst3", "iconst4", "iconst5", "lconst0", "lconst1", "fconst0", "fconst1", "fconst2", "dconst0", "dconst1", "bipush", "sipush", "ldc", "ldcw", "ldc2w", "iload", "lload", "fload", "dload", "aload", "iload0", "iload1", "iload2", "iload3", "lload0", "lload1", "lload2", "lload3", "fload0", "fload1", "fload2", "fload3", "dload0", "dload1", "dload2", "dload3", "aload0", "aload1", "aload2", "aload3", "iaload", "laload", "faload", "daload", "aaload", "baload", "caload", "saload", "istore", "lstore", "fstore", "dstore", "astore", "istore0", "istore1", "istore2", "istore3", "lstore0", "lstore1", "lstore2", "lstore3", "fstore0", "fstore1", "fstore2", "fstore3", "dstore0", "dstore1", "dstore2", "dstore3", "astore0", "astore1", "astore2", "astore3", "iastore", "lastore", "fastore", "dastore", "aastore", "bastore", "castore", "sastore", "pop", "pop2", "dup", "dupx1", "dupx2", "dup2", "dup2x1", "dup2x2", "swap", "iadd", "ladd", "fadd", "dadd", "isub", "lsub", "fsub", "dsub", "imul", "lmul", "fmul", "dmul", "idiv", "ldiv", "fdiv", "ddiv", "irem", "lrem", "frem", "drem", "ineg", "lneg", "fneg", "dneg", "ishl", "lshl", "ishr", "lshr", "iushr", "lushr", "iand", "land", "ior", "lor", "ixor", "lxor", "iinc", "i2l", "i2f", "i2d", "l2i", "l2f", "l2d", "f2i", "f2l", "f2d", "d2i", "d2l", "d2f", "i2b", "i2c", "i2s", "lcmp", "fcmpl", "fcmpg", "dcmpl", "dcmpg", "ifeq", "ifne", "iflt", "ifge", "ifgt", "ifle", "ificmpeq", "ificmpne", "ificmplt", "ificmpge", "ificmpgt", "ificmple", "ifacmpeq", "ifacmpne", "goto", "jsr", "ret", "tableswitch", "lookupswitch", "ireturn", "lreturn", "freturn", "dreturn", "areturn", "return", "getstatic", "putstatic", "getfield", "putfield", "invokevirtual", "invokespecial", "invokestatic", "invokeinterface", "invokedynamic", "new", "newarray", "anewarray", "arraylength", "athrow", "checkcast", "instanceof", "monitorenter", "monitorexit", "wide", "multianewarray", "ifnull", "ifnonnull", "gotow", "jsrw"};
}
